hubtel.py
hubtel-0.0.4.dist-info/METADATA
hubtel-0.0.4.dist-info/RECORD
hubtel-0.0.4.dist-info/WHEEL
hubtel-0.0.4.dist-info/top_level.txt
