Metadata-Version: 2.1
Name: hubtel
Version: 0.0.4
Summary: python interface for Hubtel's Payment Gateway
Home-page: https://github.com/mcroni/hubtel
Author: joey daniel darko
Author-email: joeydanieldarko@gmail.com
License: UNKNOWN
Platform: UNKNOWN
Classifier: Programming Language :: Python :: 3
Classifier: License :: OSI Approved :: MIT License
Classifier: Operating System :: OS Independent
Requires-Dist: requests
